data/__init__.py
feedview/__init__.py
feedview-0.0.1.dist-info/DESCRIPTION.rst
feedview-0.0.1.dist-info/METADATA
feedview-0.0.1.dist-info/RECORD
feedview-0.0.1.dist-info/WHEEL
feedview-0.0.1.dist-info/entry_points.txt
feedview-0.0.1.dist-info/metadata.json
feedview-0.0.1.dist-info/top_level.txt
tests/__init__.py
tests/all_test.py
